awesomepyutil/__init__.py
awesomepyutil/arithmetic_ops/__init__.py
awesomepyutil/arithmetic_ops/arithmetic_operations.py
awesomepyutil/arithmetic_ops/generate_date_dimention.py
awesomepyutil/finance/__init__.py
awesomepyutil/finance/binance_apis.py
awesomepyutil/finance/bse_apis.py
awesomepyutil/finance/nse_apis.py
awesomepyutil/finance/python_utils.py
awesomepyutil/gcp/__init__.py
awesomepyutil/gcp/bigquery.py
awesomepyutil/gcp/bigquery_schema.py
awesomepyutil/stock_market/__init__.py
awesomepyutil/stock_market/nse.py
awesomepyutil/stock_market/test_nse.py
awesomepyutil-0.0.2.dist-info/licenses/LICENSE
awesomepyutil-0.0.2.dist-info/METADATA
awesomepyutil-0.0.2.dist-info/WHEEL
awesomepyutil-0.0.2.dist-info/top_level.txt
awesomepyutil-0.0.2.dist-info/RECORD
