Metadata-Version: 2.4
Name: awesomepyutil
Version: 0.0.2
Summary: An awesome Python package
Home-page: https://gitlab.com/easycloudapi
Author: Indranil Pal
Author-email: info.easycloudapi@gmail.com
Project-URL: Bug Tracker, https://github.com/Indra-Learn/awesomepyutil/issues
Project-URL: repository, https://github.com/Indra-Learn/awesomepyutil
Keywords: NSE,Stock Market,GCP,AWS,AZURE,Snowflake,Office365,Cloud,Data Pipeline,ETL,ELT,SQL,Python
Classifier: Programming Language :: Python :: 3
Classifier: License :: OSI Approved :: MIT License
Classifier: Operating System :: OS Independent
Requires-Python: >=3.10
License-File: LICENSE
Requires-Dist: pandas==2.2.3
Requires-Dist: requests==2.32.3
Dynamic: license-file
